odoo/addons/partner_identification_notification/README.rst
odoo/addons/partner_identification_notification/__init__.py
odoo/addons/partner_identification_notification/__manifest__.py
odoo/addons/partner_identification_notification/data/ir_cron_data.xml
odoo/addons/partner_identification_notification/i18n/es.po
odoo/addons/partner_identification_notification/i18n/it.po
odoo/addons/partner_identification_notification/i18n/partner_identification_notification.pot
odoo/addons/partner_identification_notification/models/__init__.py
odoo/addons/partner_identification_notification/models/res_partner_id_category.py
odoo/addons/partner_identification_notification/models/res_partner_id_number.py
odoo/addons/partner_identification_notification/readme/CONTRIBUTORS.rst
odoo/addons/partner_identification_notification/readme/DESCRIPTION.rst
odoo/addons/partner_identification_notification/static/description/icon.png
odoo/addons/partner_identification_notification/static/description/index.html
odoo/addons/partner_identification_notification/views/res_partner_id_category_view.xml
odoo/addons/partner_identification_notification/views/res_partner_id_number_view.xml
odoo14_addon_partner_identification_notification-14.0.1.0.1.dev8.dist-info/METADATA
odoo14_addon_partner_identification_notification-14.0.1.0.1.dev8.dist-info/WHEEL
odoo14_addon_partner_identification_notification-14.0.1.0.1.dev8.dist-info/top_level.txt
odoo14_addon_partner_identification_notification-14.0.1.0.1.dev8.dist-info/RECORD
